[
  {
    "email": "tori@gmail.com",
    "password": "password"
  },
  {
    "email": "matt@gmail.com",
    "password": "password"
  },
  {
    "email": "lissie@gmail.com",
    "password": "password"
  },
  {
    "email": "jane@gmail.com",
    "password": "password"
  },
  {
    "email": "harold@gmail.com",
    "password": "password"
  },
  {
    "email": "phil@gmail.com",
    "password": "password"
  },
  {
    "email": "nori@gmail.com",
    "password": "password"
  },
  {
    "email": "paxton@gmail.com",
    "password": "password"
  }
]